<?xml version="1.0" encoding="utf-8" standalone="yes"?>
<Gesture Name = "2">
	<Stroke>
		<Point X = "218" Y = "-313" T = "0" Pressure = "0" />
		<Point X = "239" Y = "-309" T = "0" Pressure = "0" />
		<Point X = "296" Y = "-303" T = "0" Pressure = "0" />
		<Point X = "321" Y = "-301" T = "0" Pressure = "0" />
		<Point X = "390" Y = "-301" T = "0" Pressure = "0" />
		<Point X = "409" Y = "-301" T = "0" Pressure = "0" />
		<Point X = "447" Y = "-301" T = "0" Pressure = "0" />
		<Point X = "447" Y = "-301" T = "0" Pressure = "0" />
		<Point X = "447" Y = "-300" T = "0" Pressure = "0" />
		<Point X = "441" Y = "-296" T = "0" Pressure = "0" />
		<Point X = "420" Y = "-288" T = "0" Pressure = "0" />
		<Point X = "376" Y = "-271" T = "0" Pressure = "0" />
		<Point X = "321" Y = "-244" T = "0" Pressure = "0" />
		<Point X = "266" Y = "-216" T = "0" Pressure = "0" />
		<Point X = "218" Y = "-187" T = "0" Pressure = "0" />
		<Point X = "186" Y = "-169" T = "0" Pressure = "0" />
		<Point X = "169" Y = "-159" T = "0" Pressure = "0" />
		<Point X = "156" Y = "-151" T = "0" Pressure = "0" />
		<Point X = "153" Y = "-148" T = "0" Pressure = "0" />
		<Point X = "153" Y = "-147" T = "0" Pressure = "0" />
		<Point X = "153" Y = "-147" T = "0" Pressure = "0" />
		<Point X = "154" Y = "-147" T = "0" Pressure = "0" />
		<Point X = "160" Y = "-147" T = "0" Pressure = "0" />
		<Point X = "176" Y = "-147" T = "0" Pressure = "0" />
		<Point X = "201" Y = "-147" T = "0" Pressure = "0" />
		<Point X = "232" Y = "-147" T = "0" Pressure = "0" />
		<Point X = "258" Y = "-147" T = "0" Pressure = "0" />
		<Point X = "276" Y = "-146" T = "0" Pressure = "0" />
	</Stroke>
</Gesture>
